{
 "actions": [],
 "allow_rename": 1,
 "creation": "2022-07-27 14:17:14.482247",
 "doctype": "DocType",
 "editable_grid": 1,
 "engine": "InnoDB",
 "field_order": [
  "item_code",
  "description",
  "column_break_3",
  "assigned",
  "returned",
  "returned_qty",
  "target_warehouse",
  "stock_uom",
  "price"
 ],
 "fields": [
  {
   "fieldname": "item_code",
   "fieldtype": "Link",
   "in_list_view": 1,
   "label": "Item Code",
   "options": "Item",
   "read_only": 1,
   "reqd": 1
  },
  {
   "fetch_from": "item_code.item_name",
   "fieldname": "description",
   "fieldtype": "Data",
   "in_list_view": 1,
   "label": "Description",
   "read_only": 1,
   "reqd": 1
  },
  {
   "fieldname": "returned",
   "fieldtype": "Float",
   "in_list_view": 1,
   "label": "Returned",
   "reqd": 1
  },
  {
   "fieldname": "assigned",
   "fieldtype": "Float",
   "in_list_view": 1,
   "label": "Assigned",
   "read_only": 1,
   "reqd": 1
  },
  {
   "fieldname": "column_break_3",
   "fieldtype": "Column Break"
  },
  {
   "fieldname": "stock_uom",
   "fieldtype": "Data",
   "label": "UOM",
   "read_only": 1,
   "reqd": 1
  },
  {
   "fieldname": "price",
   "fieldtype": "Data",
   "label": "Price",
   "read_only": 1,
   "reqd": 1
  },
  {
   "fieldname": "target_warehouse",
   "fieldtype": "Data",
   "label": "Target Warehouse",
   "read_only": 1,
   "reqd": 1
  },
  {
   "fieldname": "returned_qty",
   "fieldtype": "Float",
   "label": "Returned Qty",
   "read_only": 1
  }
 ],
 "index_web_pages_for_search": 1,
 "istable": 1,
 "links": [],
 "modified": "2022-08-07 17:28:22.961793",
 "modified_by": "Administrator",
 "module": "Geslog",
 "name": "Geslog Material Return Item",
 "owner": "Administrator",
 "permissions": [],
 "sort_field": "modified",
 "sort_order": "DESC"
}